media_organizer/__init__.py
media_organizer/mo.py
media_organizer/config/__init__.py
media_organizer/config/config.py
media_organizer/db_operation/__init__.py
media_organizer/db_operation/db_operation.py
media_organizer/db_operation/db_reload.py
media_organizer/execution/__init__.py
media_organizer/execution/execution.py
media_organizer/file_operation/__init__.py
media_organizer/file_operation/file_operation.py
media_organizer/general_format/__init__.py
media_organizer/general_format/general_format.py
media_organizer/metadata/__init__.py
media_organizer/metadata/metadata.py
media_organizer/parse/__init__.py
media_organizer/parse/parse.py
media_organizer/report/__init__.py
media_organizer/report/report.py
media_organizer/setup_env/__init__.py
media_organizer/setup_env/setup_env.py
media_organizer/utils/__init__.py
media_organizer/utils/utils.py
media_organizer-1.1.1.data/scripts/mo
media_organizer-1.1.1.dist-info/LICENSE
media_organizer-1.1.1.dist-info/METADATA
media_organizer-1.1.1.dist-info/WHEEL
media_organizer-1.1.1.dist-info/top_level.txt
media_organizer-1.1.1.dist-info/RECORD
