Metadata-Version: 2.1
Name: media-organizer
Version: 1.1.1
Summary: This project will help you organize all of your medias, which means, basically, pictures and videos.
Home-page: https://github.com/MultiMedia-Management/media-organizer
Author: Waldirio
Author-email: waldirio@gmail.com
Classifier: Programming Language :: Python :: 3
Classifier: License :: OSI Approved :: MIT License
Classifier: Operating System :: OS Independent
Requires-Python: >=3.11
License-File: LICENSE
Requires-Dist: altgraph ==0.17.3
Requires-Dist: astroid ==2.15.6
Requires-Dist: click ==8.1.7
Requires-Dist: dill ==0.3.7
Requires-Dist: exif ==1.6.0
Requires-Dist: flake8 ==6.1.0
Requires-Dist: isort ==5.12.0
Requires-Dist: lazy-object-proxy ==1.9.0
Requires-Dist: mccabe ==0.7.0
Requires-Dist: platformdirs ==3.10.0
Requires-Dist: plum-py ==0.8.7
Requires-Dist: pycodestyle ==2.11.0
Requires-Dist: PyExifTool ==0.5.5
Requires-Dist: pyflakes ==3.1.0
Requires-Dist: pyinstaller ==5.13.1
Requires-Dist: pyinstaller-hooks-contrib ==2023.7
Requires-Dist: pylint ==2.17.5
Requires-Dist: tomlkit ==0.12.1
Requires-Dist: wrapt ==1.15.0
